example_registry/__init__.py
example_registry/csv.py
example_registry/validator.py
synapsegenie/__init__.py
synapsegenie/__main__.py
synapsegenie/__version__.py
synapsegenie/bootstrap.py
synapsegenie/config.py
synapsegenie/example_filetype_format.py
synapsegenie/input_to_database.py
synapsegenie/process_functions.py
synapsegenie/validate.py
synapsegenie/write_invalid_reasons.py
tests/__init__.py
tests/test_cli.py
tests/test_input_to_database.py
tests/test_process_functions.py
tests/test_validate.py
tests/test_write_invalid_reasons.py
synapsegenie-0.0.2.dist-info/LICENSE
synapsegenie-0.0.2.dist-info/METADATA
synapsegenie-0.0.2.dist-info/WHEEL
synapsegenie-0.0.2.dist-info/entry_points.txt
synapsegenie-0.0.2.dist-info/top_level.txt
synapsegenie-0.0.2.dist-info/RECORD
