Metadata-Version: 2.1
Name: synapsegenie
Version: 0.0.2
Summary: Synapse flat file validation and processing pipeline
Home-page: https://github.com/Sage-Bionetworks/synapsegenie
Author: Thomas Yu
Author-email: thomas.yu@sagebionetworks.org
License: MIT
Platform: UNKNOWN
Requires-Python: >=3.6
License-File: LICENSE
Requires-Dist: pandas (>=1.0)
Requires-Dist: synapseclient (>=2.2.2)
